segmentdetect/__init__.py
segmentdetect/gui.py
segmentdetect/segmenter.py
simpleclipsegmentation-1.0.1.dist-info/METADATA
simpleclipsegmentation-1.0.1.dist-info/WHEEL
simpleclipsegmentation-1.0.1.dist-info/top_level.txt
simpleclipsegmentation-1.0.1.dist-info/RECORD
